aws_cutom_monitoring/__init__.py
aws_cutom_monitoring/custom_monitoring.py
cloudwatch_package_dchatter-0.0.1.dist-info/LICENSE
cloudwatch_package_dchatter-0.0.1.dist-info/METADATA
cloudwatch_package_dchatter-0.0.1.dist-info/WHEEL
cloudwatch_package_dchatter-0.0.1.dist-info/top_level.txt
cloudwatch_package_dchatter-0.0.1.dist-info/RECORD
