Metadata-Version: 2.1
Name: cloudwatch-package-dchatter
Version: 0.0.1
Summary: A package to import all the use default use cases of AWS cloud watch and more.
Home-page: https://github.com/dibyanshuchatterjee/AWS-cloud-watch-custom-metrics-monitoring.
Author: Dibyanshu Chatterjee
Author-email: dibyanshu.chatterjee.27@gmail.com
Classifier: Programming Language :: Python :: 3
Classifier: License :: OSI Approved :: MIT License
Classifier: Operating System :: OS Independent
Requires-Python: >=3.6
License-File: LICENSE
